uv2json/__init__.py
uv2json/__main__.py
uv2json/uv2json.py
uv2json-1.0.3.dist-info/LICENSE
uv2json-1.0.3.dist-info/METADATA
uv2json-1.0.3.dist-info/WHEEL
uv2json-1.0.3.dist-info/entry_points.txt
uv2json-1.0.3.dist-info/top_level.txt
uv2json-1.0.3.dist-info/RECORD
