Metadata-Version: 2.1
Name: uv2json
Version: 1.0.3
Summary: Convert Gilson CSV files to JSON
Home-page: https://github.com/chanana/uv2json
Author: Shaurya Chanana
Author-email: schanana@wisc.edu
License: UNKNOWN
Project-URL: Bug Tracker, https://github.com/chanana/uv2json/issues
Platform: UNKNOWN
Classifier: Programming Language :: Python :: 3
Classifier: Operating System :: OS Independent
Classifier: License :: OSI Approved :: GNU Lesser General Public License v3 (LGPLv3)
Requires-Python: >=3.8
License-File: LICENSE
Requires-Dist: pandas (>=1.3.1)
